{
	"configurations" : 
	[
		{
			"directories" : 
			[
				{
					"build" : ".",
					"jsonFile" : "directory-.-Debug-d0094a50bb2071803777.json",
					"minimumCMakeVersion" : 
					{
						"string" : "3.16"
					},
					"projectIndex" : 0,
					"source" : ".",
					"targetIndexes" : 
					[
						0,
						1,
						2
					]
				}
			],
			"name" : "Debug",
			"projects" : 
			[
				{
					"directoryIndexes" : 
					[
						0
					],
					"name" : "QuickOrder",
					"targetIndexes" : 
					[
						0,
						1,
						2
					]
				}
			],
			"targets" : 
			[
				{
					"directoryIndex" : 0,
					"id" : "QuickOrder::@6890427a1f51a3e7e1df",
					"jsonFile" : "target-QuickOrder-Debug-4161ab2dee89c2ae621c.json",
					"name" : "QuickOrder",
					"projectIndex" : 0
				},
				{
					"directoryIndex" : 0,
					"id" : "QuickOrder_autogen::@6890427a1f51a3e7e1df",
					"jsonFile" : "target-QuickOrder_autogen-Debug-fc8175750ab504015088.json",
					"name" : "QuickOrder_autogen",
					"projectIndex" : 0
				},
				{
					"directoryIndex" : 0,
					"id" : "QuickOrder_autogen_timestamp_deps::@6890427a1f51a3e7e1df",
					"jsonFile" : "target-QuickOrder_autogen_timestamp_deps-Debug-5bdb7cb07d7f5c300048.json",
					"name" : "QuickOrder_autogen_timestamp_deps",
					"projectIndex" : 0
				}
			]
		}
	],
	"kind" : "codemodel",
	"paths" : 
	{
		"build" : "F:/Victor/projAnaliseSist/QuickOrder/qtQuickOrder/build-QuickOrder-Desktop_Qt_6_2_1_MinGW_64_bit-Debug",
		"source" : "F:/Victor/projAnaliseSist/QuickOrder/qtQuickOrder/QuickOrder"
	},
	"version" : 
	{
		"major" : 2,
		"minor" : 3
	}
}
